{
  "version": 2,
  "description": "月龄活动模式基准数据，支持分时段预测",
  "source": "参考育儿书籍和儿科医生建议整理",
  "patterns": [
    {
      "week": 0,
      "activityType": 0,
      "global": { "intervalMinutes": 150, "durationMinutes": 25, "countPerDay": 10 },
      "timeSlots": {
        "morning": { "intervalMinutes": 120, "durationMinutes": 28 },
        "forenoon": { "intervalMinutes": 150, "durationMinutes": 25 },
        "afternoon": { "intervalMinutes": 150, "durationMinutes": 25 },
        "evening": { "intervalMinutes": 180, "durationMinutes": 22 },
        "night": { "intervalMinutes": 240, "durationMinutes": 25 }
      },
      "notes": "新生儿按需喂养"
    },
    {
      "week": 0,
      "activityType": 2,
      "global": { "intervalMinutes": 90, "durationMinutes": 120, "countPerDay": 8 },
      "timeSlots": {
        "morning": { "intervalMinutes": 90, "durationMinutes": 90 },
        "forenoon": { "intervalMinutes": 90, "durationMinutes": 120 },
        "afternoon": { "intervalMinutes": 90, "durationMinutes": 150 },
        "evening": { "intervalMinutes": 90, "durationMinutes": 90 },
        "night": { "intervalMinutes": 60, "durationMinutes": 180 }
      },
      "notes": "新生儿大部分时间在睡眠"
    },
    {
      "week": 0,
      "activityType": 3,
      "global": { "intervalMinutes": 180, "durationMinutes": null, "countPerDay": 6 },
      "timeSlots": {
        "morning": { "intervalMinutes": 150 },
        "forenoon": { "intervalMinutes": 180 },
        "afternoon": { "intervalMinutes": 180 },
        "evening": { "intervalMinutes": 200 },
        "night": { "intervalMinutes": 240 }
      },
      "notes": "新生儿每天约6-8次尿布更换"
    },

    {
      "week": 1,
      "activityType": 0,
      "global": { "intervalMinutes": 150, "durationMinutes": 28, "countPerDay": 10 },
      "timeSlots": {
        "morning": { "intervalMinutes": 120, "durationMinutes": 30 },
        "forenoon": { "intervalMinutes": 150, "durationMinutes": 28 },
        "afternoon": { "intervalMinutes": 150, "durationMinutes": 28 },
        "evening": { "intervalMinutes": 180, "durationMinutes": 25 },
        "night": { "intervalMinutes": 240, "durationMinutes": 28 }
      },
      "notes": "喂养时间略有延长"
    },
    {
      "week": 1,
      "activityType": 2,
      "global": { "intervalMinutes": 90, "durationMinutes": 120, "countPerDay": 8 },
      "timeSlots": {
        "morning": { "intervalMinutes": 90, "durationMinutes": 100 },
        "forenoon": { "intervalMinutes": 100, "durationMinutes": 120 },
        "afternoon": { "intervalMinutes": 90, "durationMinutes": 140 },
        "evening": { "intervalMinutes": 100, "durationMinutes": 100 },
        "night": { "intervalMinutes": 60, "durationMinutes": 180 }
      },
      "notes": "睡眠时间略有缩短"
    },
    {
      "week": 1,
      "activityType": 3,
      "global": { "intervalMinutes": 180, "durationMinutes": null, "countPerDay": 6 },
      "timeSlots": {
        "morning": { "intervalMinutes": 150 },
        "forenoon": { "intervalMinutes": 180 },
        "afternoon": { "intervalMinutes": 180 },
        "evening": { "intervalMinutes": 200 },
        "night": { "intervalMinutes": 240 }
      },
      "notes": "排泄次数稳定"
    },

    {
      "week": 2,
      "activityType": 0,
      "global": { "intervalMinutes": 150, "durationMinutes": 30, "countPerDay": 9 },
      "timeSlots": {
        "morning": { "intervalMinutes": 130, "durationMinutes": 32 },
        "forenoon": { "intervalMinutes": 150, "durationMinutes": 30 },
        "afternoon": { "intervalMinutes": 150, "durationMinutes": 30 },
        "evening": { "intervalMinutes": 190, "durationMinutes": 28 },
        "night": { "intervalMinutes": 250, "durationMinutes": 30 }
      },
      "notes": "喂养效率提高"
    },
    {
      "week": 2,
      "activityType": 2,
      "global": { "intervalMinutes": 100, "durationMinutes": 115, "countPerDay": 7 },
      "timeSlots": {
        "morning": { "intervalMinutes": 100, "durationMinutes": 90 },
        "forenoon": { "intervalMinutes": 110, "durationMinutes": 110 },
        "afternoon": { "intervalMinutes": 100, "durationMinutes": 130 },
        "evening": { "intervalMinutes": 110, "durationMinutes": 100 },
        "night": { "intervalMinutes": 70, "durationMinutes": 180 }
      },
      "notes": "清醒时间逐渐增加"
    },
    {
      "week": 2,
      "activityType": 3,
      "global": { "intervalMinutes": 180, "durationMinutes": null, "countPerDay": 6 },
      "timeSlots": {
        "morning": { "intervalMinutes": 160 },
        "forenoon": { "intervalMinutes": 180 },
        "afternoon": { "intervalMinutes": 180 },
        "evening": { "intervalMinutes": 200 },
        "night": { "intervalMinutes": 250 }
      },
      "notes": "排泄次数稳定"
    },

    {
      "week": 3,
      "activityType": 0,
      "global": { "intervalMinutes": 160, "durationMinutes": 32, "countPerDay": 9 },
      "timeSlots": {
        "morning": { "intervalMinutes": 140, "durationMinutes": 34 },
        "forenoon": { "intervalMinutes": 160, "durationMinutes": 32 },
        "afternoon": { "intervalMinutes": 160, "durationMinutes": 32 },
        "evening": { "intervalMinutes": 200, "durationMinutes": 30 },
        "night": { "intervalMinutes": 260, "durationMinutes": 32 }
      },
      "notes": "喂养间隔延长"
    },
    {
      "week": 3,
      "activityType": 2,
      "global": { "intervalMinutes": 100, "durationMinutes": 110, "countPerDay": 7 },
      "timeSlots": {
        "morning": { "intervalMinutes": 100, "durationMinutes": 85 },
        "forenoon": { "intervalMinutes": 110, "durationMinutes": 105 },
        "afternoon": { "intervalMinutes": 100, "durationMinutes": 125 },
        "evening": { "intervalMinutes": 120, "durationMinutes": 95 },
        "night": { "intervalMinutes": 80, "durationMinutes": 180 }
      },
      "notes": "睡眠时间略有减少"
    },
    {
      "week": 3,
      "activityType": 3,
      "global": { "intervalMinutes": 190, "durationMinutes": null, "countPerDay": 6 },
      "timeSlots": {
        "morning": { "intervalMinutes": 170 },
        "forenoon": { "intervalMinutes": 190 },
        "afternoon": { "intervalMinutes": 190 },
        "evening": { "intervalMinutes": 210 },
        "night": { "intervalMinutes": 260 }
      },
      "notes": "排泄间隔略延长"
    },

    {
      "week": 4,
      "activityType": 0,
      "global": { "intervalMinutes": 170, "durationMinutes": 35, "countPerDay": 8 },
      "timeSlots": {
        "morning": { "intervalMinutes": 150, "durationMinutes": 38 },
        "forenoon": { "intervalMinutes": 170, "durationMinutes": 35 },
        "afternoon": { "intervalMinutes": 170, "durationMinutes": 35 },
        "evening": { "intervalMinutes": 210, "durationMinutes": 32 },
        "night": { "intervalMinutes": 280, "durationMinutes": 35 }
      },
      "notes": "满月宝宝喂养间隔约2.5-3小时"
    },
    {
      "week": 4,
      "activityType": 2,
      "global": { "intervalMinutes": 110, "durationMinutes": 105, "countPerDay": 6 },
      "timeSlots": {
        "morning": { "intervalMinutes": 110, "durationMinutes": 80 },
        "forenoon": { "intervalMinutes": 120, "durationMinutes": 100 },
        "afternoon": { "intervalMinutes": 110, "durationMinutes": 120 },
        "evening": { "intervalMinutes": 130, "durationMinutes": 90 },
        "night": { "intervalMinutes": 90, "durationMinutes": 180 }
      },
      "notes": "睡眠逐渐规律"
    },
    {
      "week": 4,
      "activityType": 3,
      "global": { "intervalMinutes": 200, "durationMinutes": null, "countPerDay": 5 },
      "timeSlots": {
        "morning": { "intervalMinutes": 180 },
        "forenoon": { "intervalMinutes": 200 },
        "afternoon": { "intervalMinutes": 200 },
        "evening": { "intervalMinutes": 220 },
        "night": { "intervalMinutes": 280 }
      },
      "notes": "排泄次数略有减少"
    },

    {
      "week": 5,
      "activityType": 0,
      "global": { "intervalMinutes": 180, "durationMinutes": 35, "countPerDay": 8 },
      "timeSlots": {
        "morning": { "intervalMinutes": 160, "durationMinutes": 38 },
        "forenoon": { "intervalMinutes": 180, "durationMinutes": 35 },
        "afternoon": { "intervalMinutes": 180, "durationMinutes": 35 },
        "evening": { "intervalMinutes": 220, "durationMinutes": 32 },
        "night": { "intervalMinutes": 300, "durationMinutes": 35 }
      },
      "notes": "喂养间隔约3小时"
    },
    {
      "week": 5,
      "activityType": 2,
      "global": { "intervalMinutes": 110, "durationMinutes": 100, "countPerDay": 6 },
      "timeSlots": {
        "morning": { "intervalMinutes": 110, "durationMinutes": 75 },
        "forenoon": { "intervalMinutes": 120, "durationMinutes": 95 },
        "afternoon": { "intervalMinutes": 110, "durationMinutes": 115 },
        "evening": { "intervalMinutes": 140, "durationMinutes": 85 },
        "night": { "intervalMinutes": 100, "durationMinutes": 180 }
      },
      "notes": "睡眠时间减少"
    },
    {
      "week": 5,
      "activityType": 3,
      "global": { "intervalMinutes": 200, "durationMinutes": null, "countPerDay": 5 },
      "timeSlots": {
        "morning": { "intervalMinutes": 180 },
        "forenoon": { "intervalMinutes": 200 },
        "afternoon": { "intervalMinutes": 200 },
        "evening": { "intervalMinutes": 230 },
        "night": { "intervalMinutes": 300 }
      },
      "notes": "排泄间隔延长"
    },

    {
      "week": 6,
      "activityType": 0,
      "global": { "intervalMinutes": 180, "durationMinutes": 35, "countPerDay": 7 },
      "timeSlots": {
        "morning": { "intervalMinutes": 160, "durationMinutes": 38 },
        "forenoon": { "intervalMinutes": 180, "durationMinutes": 35 },
        "afternoon": { "intervalMinutes": 180, "durationMinutes": 35 },
        "evening": { "intervalMinutes": 230, "durationMinutes": 32 },
        "night": { "intervalMinutes": 320, "durationMinutes": 35 }
      },
      "notes": "喂养间隔约3小时"
    },
    {
      "week": 6,
      "activityType": 2,
      "global": { "intervalMinutes": 120, "durationMinutes": 95, "countPerDay": 5 },
      "timeSlots": {
        "morning": { "intervalMinutes": 120, "durationMinutes": 70 },
        "forenoon": { "intervalMinutes": 130, "durationMinutes": 90 },
        "afternoon": { "intervalMinutes": 120, "durationMinutes": 110 },
        "evening": { "intervalMinutes": 150, "durationMinutes": 80 },
        "night": { "intervalMinutes": 110, "durationMinutes": 180 }
      },
      "notes": "白天清醒时间增加"
    },
    {
      "week": 6,
      "activityType": 3,
      "global": { "intervalMinutes": 210, "durationMinutes": null, "countPerDay": 5 },
      "timeSlots": {
        "morning": { "intervalMinutes": 190 },
        "forenoon": { "intervalMinutes": 210 },
        "afternoon": { "intervalMinutes": 210 },
        "evening": { "intervalMinutes": 240 },
        "night": { "intervalMinutes": 320 }
      },
      "notes": "排泄间隔继续延长"
    },

    {
      "week": 7,
      "activityType": 0,
      "global": { "intervalMinutes": 190, "durationMinutes": 35, "countPerDay": 7 },
      "timeSlots": {
        "morning": { "intervalMinutes": 170, "durationMinutes": 38 },
        "forenoon": { "intervalMinutes": 190, "durationMinutes": 35 },
        "afternoon": { "intervalMinutes": 190, "durationMinutes": 35 },
        "evening": { "intervalMinutes": 240, "durationMinutes": 32 },
        "night": { "intervalMinutes": 340, "durationMinutes": 35 }
      },
      "notes": "喂养效率提高"
    },
    {
      "week": 7,
      "activityType": 2,
      "global": { "intervalMinutes": 120, "durationMinutes": 90, "countPerDay": 5 },
      "timeSlots": {
        "morning": { "intervalMinutes": 120, "durationMinutes": 65 },
        "forenoon": { "intervalMinutes": 130, "durationMinutes": 85 },
        "afternoon": { "intervalMinutes": 120, "durationMinutes": 105 },
        "evening": { "intervalMinutes": 160, "durationMinutes": 75 },
        "night": { "intervalMinutes": 120, "durationMinutes": 180 }
      },
      "notes": "睡眠更加规律"
    },
    {
      "week": 7,
      "activityType": 3,
      "global": { "intervalMinutes": 220, "durationMinutes": null, "countPerDay": 5 },
      "timeSlots": {
        "morning": { "intervalMinutes": 200 },
        "forenoon": { "intervalMinutes": 220 },
        "afternoon": { "intervalMinutes": 220 },
        "evening": { "intervalMinutes": 250 },
        "night": { "intervalMinutes": 340 }
      },
      "notes": "排泄间隔约3.5小时"
    },

    {
      "week": 8,
      "activityType": 0,
      "global": { "intervalMinutes": 200, "durationMinutes": 35, "countPerDay": 7 },
      "timeSlots": {
        "morning": { "intervalMinutes": 180, "durationMinutes": 38 },
        "forenoon": { "intervalMinutes": 200, "durationMinutes": 35 },
        "afternoon": { "intervalMinutes": 200, "durationMinutes": 35 },
        "evening": { "intervalMinutes": 250, "durationMinutes": 32 },
        "night": { "intervalMinutes": 360, "durationMinutes": 35 }
      },
      "notes": "2个月宝宝喂养间隔约3-3.5小时"
    },
    {
      "week": 8,
      "activityType": 2,
      "global": { "intervalMinutes": 130, "durationMinutes": 85, "countPerDay": 5 },
      "timeSlots": {
        "morning": { "intervalMinutes": 130, "durationMinutes": 60 },
        "forenoon": { "intervalMinutes": 140, "durationMinutes": 80 },
        "afternoon": { "intervalMinutes": 130, "durationMinutes": 100 },
        "evening": { "intervalMinutes": 170, "durationMinutes": 70 },
        "night": { "intervalMinutes": 130, "durationMinutes": 180 }
      },
      "notes": "白天小睡次数减少"
    },
    {
      "week": 8,
      "activityType": 3,
      "global": { "intervalMinutes": 220, "durationMinutes": null, "countPerDay": 5 },
      "timeSlots": {
        "morning": { "intervalMinutes": 200 },
        "forenoon": { "intervalMinutes": 220 },
        "afternoon": { "intervalMinutes": 220 },
        "evening": { "intervalMinutes": 260 },
        "night": { "intervalMinutes": 360 }
      },
      "notes": "排泄间隔约3.5小时"
    },

    {
      "week": 12,
      "activityType": 0,
      "global": { "intervalMinutes": 220, "durationMinutes": 25, "countPerDay": 6 },
      "timeSlots": {
        "morning": { "intervalMinutes": 200, "durationMinutes": 28 },
        "forenoon": { "intervalMinutes": 220, "durationMinutes": 25 },
        "afternoon": { "intervalMinutes": 220, "durationMinutes": 25 },
        "evening": { "intervalMinutes": 280, "durationMinutes": 22 },
        "night": { "intervalMinutes": 420, "durationMinutes": 25 }
      },
      "notes": "3个月宝宝喂养间隔约3.5-4小时"
    },
    {
      "week": 12,
      "activityType": 2,
      "global": { "intervalMinutes": 150, "durationMinutes": 75, "countPerDay": 4 },
      "timeSlots": {
        "morning": { "intervalMinutes": 150, "durationMinutes": 50 },
        "forenoon": { "intervalMinutes": 160, "durationMinutes": 70 },
        "afternoon": { "intervalMinutes": 150, "durationMinutes": 90 },
        "evening": { "intervalMinutes": 200, "durationMinutes": 60 },
        "night": { "intervalMinutes": 180, "durationMinutes": 180 }
      },
      "notes": "白天小睡3次，夜间睡眠延长"
    },
    {
      "week": 12,
      "activityType": 3,
      "global": { "intervalMinutes": 240, "durationMinutes": null, "countPerDay": 4 },
      "timeSlots": {
        "morning": { "intervalMinutes": 220 },
        "forenoon": { "intervalMinutes": 240 },
        "afternoon": { "intervalMinutes": 240 },
        "evening": { "intervalMinutes": 280 },
        "night": { "intervalMinutes": 420 }
      },
      "notes": "排泄间隔约4小时"
    },

    {
      "week": 16,
      "activityType": 0,
      "global": { "intervalMinutes": 240, "durationMinutes": 20, "countPerDay": 5 },
      "timeSlots": {
        "morning": { "intervalMinutes": 220, "durationMinutes": 22 },
        "forenoon": { "intervalMinutes": 240, "durationMinutes": 20 },
        "afternoon": { "intervalMinutes": 240, "durationMinutes": 20 },
        "evening": { "intervalMinutes": 300, "durationMinutes": 18 },
        "night": { "intervalMinutes": 480, "durationMinutes": 20 }
      },
      "notes": "4个月宝宝喂养间隔约4小时"
    },
    {
      "week": 16,
      "activityType": 2,
      "global": { "intervalMinutes": 170, "durationMinutes": 65, "countPerDay": 4 },
      "timeSlots": {
        "morning": { "intervalMinutes": 170, "durationMinutes": 45 },
        "forenoon": { "intervalMinutes": 180, "durationMinutes": 60 },
        "afternoon": { "intervalMinutes": 170, "durationMinutes": 80 },
        "evening": { "intervalMinutes": 220, "durationMinutes": 50 },
        "night": { "intervalMinutes": 200, "durationMinutes": 180 }
      },
      "notes": "白天小睡3次"
    },
    {
      "week": 16,
      "activityType": 3,
      "global": { "intervalMinutes": 250, "durationMinutes": null, "countPerDay": 4 },
      "timeSlots": {
        "morning": { "intervalMinutes": 230 },
        "forenoon": { "intervalMinutes": 250 },
        "afternoon": { "intervalMinutes": 250 },
        "evening": { "intervalMinutes": 300 },
        "night": { "intervalMinutes": 480 }
      },
      "notes": "排泄间隔约4小时"
    },

    {
      "week": 20,
      "activityType": 0,
      "global": { "intervalMinutes": 260, "durationMinutes": 20, "countPerDay": 5 },
      "timeSlots": {
        "morning": { "intervalMinutes": 240, "durationMinutes": 22 },
        "forenoon": { "intervalMinutes": 260, "durationMinutes": 20 },
        "afternoon": { "intervalMinutes": 260, "durationMinutes": 20 },
        "evening": { "intervalMinutes": 320, "durationMinutes": 18 },
        "night": { "intervalMinutes": 540, "durationMinutes": 20 }
      },
      "notes": "5个月宝宝喂养间隔约4-4.5小时"
    },
    {
      "week": 20,
      "activityType": 2,
      "global": { "intervalMinutes": 190, "durationMinutes": 55, "countPerDay": 3 },
      "timeSlots": {
        "morning": { "intervalMinutes": 190, "durationMinutes": 40 },
        "forenoon": { "intervalMinutes": 200, "durationMinutes": 50 },
        "afternoon": { "intervalMinutes": 190, "durationMinutes": 70 },
        "evening": { "intervalMinutes": 240, "durationMinutes": 40 },
        "night": { "intervalMinutes": 240, "durationMinutes": 180 }
      },
      "notes": "白天小睡2-3次"
    },
    {
      "week": 20,
      "activityType": 3,
      "global": { "intervalMinutes": 270, "durationMinutes": null, "countPerDay": 4 },
      "timeSlots": {
        "morning": { "intervalMinutes": 250 },
        "forenoon": { "intervalMinutes": 270 },
        "afternoon": { "intervalMinutes": 270 },
        "evening": { "intervalMinutes": 320 },
        "night": { "intervalMinutes": 540 }
      },
      "notes": "排泄间隔约4.5小时"
    },

    {
      "week": 24,
      "activityType": 0,
      "global": { "intervalMinutes": 280, "durationMinutes": 15, "countPerDay": 5 },
      "timeSlots": {
        "morning": { "intervalMinutes": 260, "durationMinutes": 18 },
        "forenoon": { "intervalMinutes": 280, "durationMinutes": 15 },
        "afternoon": { "intervalMinutes": 280, "durationMinutes": 15 },
        "evening": { "intervalMinutes": 340, "durationMinutes": 12 },
        "night": { "intervalMinutes": 600, "durationMinutes": 15 }
      },
      "notes": "6个月宝宝开始添加辅食"
    },
    {
      "week": 24,
      "activityType": 2,
      "global": { "intervalMinutes": 210, "durationMinutes": 50, "countPerDay": 3 },
      "timeSlots": {
        "morning": { "intervalMinutes": 210, "durationMinutes": 35 },
        "forenoon": { "intervalMinutes": 220, "durationMinutes": 45 },
        "afternoon": { "intervalMinutes": 210, "durationMinutes": 60 },
        "evening": { "intervalMinutes": 260, "durationMinutes": 35 },
        "night": { "intervalMinutes": 280, "durationMinutes": 180 }
      },
      "notes": "白天小睡2次"
    },
    {
      "week": 24,
      "activityType": 3,
      "global": { "intervalMinutes": 280, "durationMinutes": null, "countPerDay": 3 },
      "timeSlots": {
        "morning": { "intervalMinutes": 260 },
        "forenoon": { "intervalMinutes": 280 },
        "afternoon": { "intervalMinutes": 280 },
        "evening": { "intervalMinutes": 340 },
        "night": { "intervalMinutes": 600 }
      },
      "notes": "排泄间隔约4.5小时，辅食后排便可能变化"
    },

    {
      "week": 32,
      "activityType": 0,
      "global": { "intervalMinutes": 320, "durationMinutes": 15, "countPerDay": 4 },
      "timeSlots": {
        "morning": { "intervalMinutes": 300, "durationMinutes": 18 },
        "forenoon": { "intervalMinutes": 320, "durationMinutes": 15 },
        "afternoon": { "intervalMinutes": 320, "durationMinutes": 15 },
        "evening": { "intervalMinutes": 380, "durationMinutes": 12 },
        "night": { "intervalMinutes": 660, "durationMinutes": 15 }
      },
      "notes": "8个月宝宝辅食更丰富"
    },
    {
      "week": 32,
      "activityType": 2,
      "global": { "intervalMinutes": 250, "durationMinutes": 40, "countPerDay": 2 },
      "timeSlots": {
        "morning": { "intervalMinutes": 250, "durationMinutes": 30 },
        "forenoon": { "intervalMinutes": 260, "durationMinutes": 35 },
        "afternoon": { "intervalMinutes": 250, "durationMinutes": 50 },
        "evening": { "intervalMinutes": 300, "durationMinutes": 25 },
        "night": { "intervalMinutes": 340, "durationMinutes": 180 }
      },
      "notes": "白天小睡2次"
    },
    {
      "week": 32,
      "activityType": 3,
      "global": { "intervalMinutes": 320, "durationMinutes": null, "countPerDay": 3 },
      "timeSlots": {
        "morning": { "intervalMinutes": 300 },
        "forenoon": { "intervalMinutes": 320 },
        "afternoon": { "intervalMinutes": 320 },
        "evening": { "intervalMinutes": 380 },
        "night": { "intervalMinutes": 660 }
      },
      "notes": "排泄间隔约5小时"
    },

    {
      "week": 40,
      "activityType": 0,
      "global": { "intervalMinutes": 360, "durationMinutes": 15, "countPerDay": 4 },
      "timeSlots": {
        "morning": { "intervalMinutes": 340, "durationMinutes": 18 },
        "forenoon": { "intervalMinutes": 360, "durationMinutes": 15 },
        "afternoon": { "intervalMinutes": 360, "durationMinutes": 15 },
        "evening": { "intervalMinutes": 420, "durationMinutes": 12 },
        "night": { "intervalMinutes": 720, "durationMinutes": 15 }
      },
      "notes": "10个月宝宝喂养间隔约6小时"
    },
    {
      "week": 40,
      "activityType": 2,
      "global": { "intervalMinutes": 290, "durationMinutes": 30, "countPerDay": 2 },
      "timeSlots": {
        "morning": { "intervalMinutes": 290, "durationMinutes": 25 },
        "forenoon": { "intervalMinutes": 300, "durationMinutes": 28 },
        "afternoon": { "intervalMinutes": 290, "durationMinutes": 40 },
        "evening": { "intervalMinutes": 340, "durationMinutes": 20 },
        "night": { "intervalMinutes": 400, "durationMinutes": 180 }
      },
      "notes": "白天小睡2次"
    },
    {
      "week": 40,
      "activityType": 3,
      "global": { "intervalMinutes": 360, "durationMinutes": null, "countPerDay": 2 },
      "timeSlots": {
        "morning": { "intervalMinutes": 340 },
        "forenoon": { "intervalMinutes": 360 },
        "afternoon": { "intervalMinutes": 360 },
        "evening": { "intervalMinutes": 420 },
        "night": { "intervalMinutes": 720 }
      },
      "notes": "排泄间隔约6小时"
    },

    {
      "week": 52,
      "activityType": 0,
      "global": { "intervalMinutes": 360, "durationMinutes": 15, "countPerDay": 3 },
      "timeSlots": {
        "morning": { "intervalMinutes": 340, "durationMinutes": 18 },
        "forenoon": { "intervalMinutes": 360, "durationMinutes": 15 },
        "afternoon": { "intervalMinutes": 360, "durationMinutes": 15 },
        "evening": { "intervalMinutes": 420, "durationMinutes": 12 },
        "night": { "intervalMinutes": 780, "durationMinutes": 15 }
      },
      "notes": "1岁宝宝每日3餐+奶"
    },
    {
      "week": 52,
      "activityType": 2,
      "global": { "intervalMinutes": 360, "durationMinutes": 30, "countPerDay": 1 },
      "timeSlots": {
        "morning": { "intervalMinutes": 360, "durationMinutes": 25 },
        "forenoon": { "intervalMinutes": 380, "durationMinutes": 28 },
        "afternoon": { "intervalMinutes": 360, "durationMinutes": 40 },
        "evening": { "intervalMinutes": 400, "durationMinutes": 20 },
        "night": { "intervalMinutes": 480, "durationMinutes": 180 }
      },
      "notes": "白天小睡1次"
    },
    {
      "week": 52,
      "activityType": 3,
      "global": { "intervalMinutes": 360, "durationMinutes": null, "countPerDay": 2 },
      "timeSlots": {
        "morning": { "intervalMinutes": 340 },
        "forenoon": { "intervalMinutes": 360 },
        "afternoon": { "intervalMinutes": 360 },
        "evening": { "intervalMinutes": 420 },
        "night": { "intervalMinutes": 780 }
      },
      "notes": "排泄间隔约6小时"
    }
  ]
}